{"http://purl.org/dc/terms/contributor": ["Angela Berthold, J\u00f6rg Drauschke, Anja Gerber, Georg Gerleigner, Frank von Hagel, Meike Hopp, Olivia Kaiser, Christoph Klose, Sabine Lang, Katharina Martin, Magdalene Schl\u00f6sser, Florian Thiery, Sarah Wagner, Bernhard Weisser, Petra Winter, Gabriele Z\u00f6llner"], "http://purl.org/dc/terms/creator": ["n4edd6f07901641bfa76d8a7fbed86df3b2", "n4edd6f07901641bfa76d8a7fbed86df3b3", "n4edd6f07901641bfa76d8a7fbed86df3b4", "n4edd6f07901641bfa76d8a7fbed86df3b5"], "http://purl.org/dc/terms/description": ["Aufgabe der Temporary Working Group innerhalb von NFDI4Objects war es, Dienste und Werkzeuge f\u00fcr Forschungssammlungen und Provenienzforschung zu identifizieren und in Katalogform online zu publizieren. Die Samlung soll als Werkzeug vor allem den Einstieg in die Sammlungsarbeit sowie Provenienzforschung erleichtern sowie relevante digitale Anwedungen sammeln und zur Verf\u00fcgung stellen.\nDiese Sammlung wurde sowohl in inhaltliche als auch in typologische Kategorien gegliedert. Diese Typen sind: Netzwerke und Services, Empfehlungen, Digitale Anwendungen sowie Recherche und Ressourcen. Die inhaltliche Einteilung erfolgte nach Kontexten, diese sind: Koloniale Konetxte, NS-Zeit, SBZ/DDR, Secret/Sacred Objects und Natukunde/Naturwissenschaft. Alle Kategorien sind \u00fcber einen Filter suchbar. Die Beschreibung der einzelnen Ressourcen wurde gr\u00f6\u00dfteneils von den entsprechenden, zitierten Quellen \u00fcbernommen und teilweise modifiziert. F\u00fcr die gesammelten und zitierten Inhalte \u00fcbernehmen die Autor*innen dieser Sammlung keine Gew\u00e4hr."], "http://purl.org/dc/terms/issued": ["2025-06-20"], "http://purl.org/dc/terms/license": ["https://creativecommons.org/licenses/by/4.0/"], "http://purl.org/dc/terms/publisher": ["Angela Berthold, Frank von Hagel, Gabriele Z\u00f6llner, Florian Thiery"], "http://purl.org/dc/terms/title": ["ta2-prov-tools-services-matrix"], "http://rdfs.org/ns/void#inDataset": ["https://w3id.org/n4o-metadata/prov-matrix/N4O_TA2_PROV_Matrix_Tools_&_Services"], "http://www.w3.org/1999/02/22-rdf-syntax-ns#type": ["http://www.w3.org/ns/dcat#Catalog"], "http://www.w3.org/ns/dcat#contactPoint": ["Angela Berthold (a.berthold@smb.spk-berlin.de)"], "http://www.w3.org/ns/dcat#keyword": ["NFDI", "NFDI4Objects", "Provenienzforschung", "Services", "Tools"], "http://www.w3.org/ns/dcat#landingPage": ["https://github.com/n4o-rse/ta2-prov-tools-services-matrix/"], "http://www.w3.org/ns/dcat#version": ["1.0"]}